MOdel/__init__.py
MOdel/load_model.py
MOdel/test.py
modelAfroz-0.1.dist-info/LICENSE
modelAfroz-0.1.dist-info/METADATA
modelAfroz-0.1.dist-info/WHEEL
modelAfroz-0.1.dist-info/top_level.txt
modelAfroz-0.1.dist-info/RECORD
